README.md
setup.py
pps/__init__.py
pps/cli.py
pps/color.py
pps/helper.py
pps/message.py
preview_pipfile_scripts.egg-info/PKG-INFO
preview_pipfile_scripts.egg-info/SOURCES.txt
preview_pipfile_scripts.egg-info/dependency_links.txt
preview_pipfile_scripts.egg-info/entry_points.txt
preview_pipfile_scripts.egg-info/requires.txt
preview_pipfile_scripts.egg-info/top_level.txt
tests/__init__.py
tests/cli_test.py
tests/helper_test.py