Metadata-Version: 2.1
Name: preview-pipfile-scripts
Version: 0.1.1
Summary: Python CLI for previewing and running Pipfile scripts
Home-page: https://github.com/SeungUkLee/pps
Author: Seunguk Lee
Author-email: lsy931106@gmail.com
License: MIT
Platform: UNKNOWN
Classifier: License :: OSI Approved :: MIT License
Classifier: Topic :: Utilities
Classifier: Development Status :: 3 - Alpha
Classifier: Environment :: Console
Classifier: Intended Audience :: Developers
